seedr_client/__init__.py
seedr_client/errors.py
seedr_client/seedr_handler.py
SeedrClient-0.1.7.dist-info/METADATA
SeedrClient-0.1.7.dist-info/WHEEL
SeedrClient-0.1.7.dist-info/top_level.txt
SeedrClient-0.1.7.dist-info/RECORD
